SMVLibreria/__init__.py
SMVLibreria/carga_datos.py
SMVLibreria/conteo_periodo.py
SMVLibreria/perfil_victimas.py
SMVLibreria/tasa.py
smvlibreria-1.0.9.dist-info/licenses/LICENSE
smvlibreria-1.0.9.dist-info/METADATA
smvlibreria-1.0.9.dist-info/WHEEL
smvlibreria-1.0.9.dist-info/top_level.txt
smvlibreria-1.0.9.dist-info/RECORD
