Metadata-Version: 2.4
Name: SMVLibreria
Version: 1.0.9
Summary: Librería para analizar datos de seguridad vial de SEMOVI: conteo por periodos y tasas de crecimiento
Home-page: https://github.com/greenmay99/semovi_libreria
Author: @may, @juan
Author-email: may@example.com, juan@example.com
License: MIT
Project-URL: Repositorio, https://github.com/greenmay99/semovi_libreria
Classifier: Programming Language :: Python :: 3
Classifier: Operating System :: OS Independent
Classifier: Topic :: Scientific/Engineering :: Information Analysis
Requires-Python: >=3.6
License-File: LICENSE
Requires-Dist: pandas
Requires-Dist: seaborn
Requires-Dist: matplotlib
Requires-Dist: requests
Dynamic: author
Dynamic: author-email
Dynamic: classifier
Dynamic: description
Dynamic: description-content-type
Dynamic: home-page
Dynamic: license
Dynamic: license-file
Dynamic: project-url
Dynamic: requires-dist
Dynamic: requires-python
Dynamic: summary
